devpi_common/__init__.py
devpi_common/archive.py
devpi_common/contextlib.py
devpi_common/metadata.py
devpi_common/py.typed
devpi_common/request.py
devpi_common/terminal.py
devpi_common/types.py
devpi_common/url.py
devpi_common/validation.py
devpi_common/viewhelp.py
devpi_common-4.1.0.dist-info/LICENSE
devpi_common-4.1.0.dist-info/METADATA
devpi_common-4.1.0.dist-info/WHEEL
devpi_common-4.1.0.dist-info/top_level.txt
devpi_common-4.1.0.dist-info/RECORD
