Metadata-Version: 2.1
Name: devpi-common
Version: 4.1.0
Summary: Utilities jointly used by devpi-server, devpi-client and others.
Maintainer-email: Florian Schulze <mail@pyfidelity.com>
License: 
Project-URL: repository, https://github.com/devpi/devpi
Classifier: Development Status :: 5 - Production/Stable
Classifier: Environment :: Web Environment
Classifier: Intended Audience :: Developers
Classifier: Intended Audience :: System Administrators
Classifier: License :: OSI Approved :: MIT License
Classifier: Programming Language :: Python :: Implementation :: PyPy
Classifier: Programming Language :: Python :: 3.7
Classifier: Programming Language :: Python :: 3.8
Classifier: Programming Language :: Python :: 3.9
Classifier: Programming Language :: Python :: 3.10
Classifier: Programming Language :: Python :: 3.11
Classifier: Programming Language :: Python :: 3.12
Requires-Python: >=3.7
License-File: LICENSE
Requires-Dist: lazy
Requires-Dist: packaging-legacy
Requires-Dist: requests >=2.3.0
